[
    {
      "title": "Ultimate Tips for Winning in Esports",
      "link": "/games/ultimate-tips-esports",
      "author": "GamerGuru",
      "date": "2023-10-05",
      "content": "This article delves into essential tips for dominating in the world of esports.",
      "image": "https://picsum.photos/201",
      "url": "https://newexample.com",
      "flair": "Guide"
    },
    {
      "title": "Must-Play Card Games of 2023",
      "link": "/games/must-play-card-games-2023",
      "author": "BoardGameBuff",
      "date": "2023-10-06",
      "content": "Join us as we highlight the must-play card games that are trending this year.",
      "image": "https://picsum.photos/201",
      "url": "https://newexample.com",
      "flair": "Review"
    }
]
